ezexcel.py
ezexcel-0.1.1.dist-info/LICENSE
ezexcel-0.1.1.dist-info/METADATA
ezexcel-0.1.1.dist-info/WHEEL
ezexcel-0.1.1.dist-info/top_level.txt
ezexcel-0.1.1.dist-info/RECORD
