Metadata-Version: 2.1
Name: ezexcel
Version: 0.1.1
Summary: A simple class based xlsx serialization system
Home-page: https://github.com/Descent098/ezexcel
Author: Kieran Wood
Author-email: kieran@canadiancoding.ca
License: UNKNOWN
Platform: UNKNOWN
Classifier: Programming Language :: Python :: 3
Classifier: Operating System :: OS Independent
Classifier: Development Status :: 4 - Beta
Requires-Dist: openpyxl
Requires-Dist: colored
Provides-Extra: dev
Requires-Dist: nox ; extra == 'dev'
Requires-Dist: pytest ; extra == 'dev'
